timesheet_tool/__init__.py
timesheet_tool/config.py
timesheet_tool/jira_worklogs.py
timesheet_tool/main.py
timesheet_tool/toggl.py
timesheet_tool/tests/__init__.py
timesheet_tool/tests/test_toggl.py
timesheet_tool-0.2.0.dist-info/LICENSE
timesheet_tool-0.2.0.dist-info/METADATA
timesheet_tool-0.2.0.dist-info/WHEEL
timesheet_tool-0.2.0.dist-info/top_level.txt
timesheet_tool-0.2.0.dist-info/RECORD
