Metadata-Version: 2.1
Name: timesheet-tool
Version: 0.2.0
Summary: This is intended to be used every week to compile your time in Jira and Clockify.
Requires-Python: >=3.12
License-File: LICENSE
Requires-Dist: bandit ==1.7.5
Requires-Dist: black ==23.3.0
Requires-Dist: flake8 ==6.0.0
Requires-Dist: isort ==5.12.0
Requires-Dist: jira ==3.5.0
Requires-Dist: pytest ==7.3.1
Requires-Dist: python-dotenv ==1.0.0
Requires-Dist: pytz ==2023.3
Requires-Dist: requests ==2.28.2
